p3bamboo/BamFactory.py
p3bamboo/BamFile.py
p3bamboo/BamGlobals.py
p3bamboo/BamObject.py
p3bamboo/StructDatagram.py
p3bamboo/__init__.py
p3bamboo-1.0.9.dist-info/LICENSE
p3bamboo-1.0.9.dist-info/METADATA
p3bamboo-1.0.9.dist-info/WHEEL
p3bamboo-1.0.9.dist-info/top_level.txt
p3bamboo-1.0.9.dist-info/RECORD
