Metadata-Version: 2.1
Name: p3bamboo
Version: 1.0.9
Summary: Panda3D BAM file parser library
Home-page: https://github.com/darktohka/p3bamboo
Author: darktohka
Author-email: daniel@tohka.us
Classifier: Programming Language :: Python :: 3
Classifier: Operating System :: OS Independent
Requires-Python: >=3.6
License-File: LICENSE
